rusty_logger-0.3.0.dist-info/METADATA
rusty_logger-0.3.0.dist-info/WHEEL
rusty_logger-0.3.0.dist-info/license_files/LICENSE.md
rusty_logger/_rusty_logger.pyi
rusty_logger/__init__.py
rusty_logger/version.py
rusty_logger/_rusty_logger.cpython-310-x86_64-linux-gnu.so
rusty_logger-0.3.0.dist-info/RECORD
